ppsc/__init__.py
ppsc/_api.py
ppsc/_timestamp.py
ppsc/parse/__init__.py
ppsc/parse/_io.py
ppsc/parse/_pb.py
ppsc/parse/_test_util.py
ppsc/parse/_util.py
ppsc/parse/json/__init__.py
ppsc/parse/json/_json.py
ppsc/v202/__init__.py
ppsc/v202/_base.py
ppsc/v202/_biosample.py
ppsc/v202/_disease.py
ppsc/v202/_gene_descriptor.py
ppsc/v202/_individual.py
ppsc/v202/_interpretation.py
ppsc/v202/_measurement.py
ppsc/v202/_medical_action.py
ppsc/v202/_meta_data.py
ppsc/v202/_phenopackets.py
ppsc/v202/_phenotypic_feature.py
ppsc/v202/_test_individual.py
ppsc/v202/_vrs.py
ppsc/v202/_vrsatile.py
ga4gh_phenopacket_core-0.1.0.dist-info/METADATA
ga4gh_phenopacket_core-0.1.0.dist-info/WHEEL
ga4gh_phenopacket_core-0.1.0.dist-info/top_level.txt
ga4gh_phenopacket_core-0.1.0.dist-info/RECORD
